triton_util/__init__.py
triton_util/coding.py
triton_util/debugging.py
triton_util-0.0.2.dist-info/METADATA
triton_util-0.0.2.dist-info/WHEEL
triton_util-0.0.2.dist-info/top_level.txt
triton_util-0.0.2.dist-info/RECORD
