Metadata-Version: 2.1
Name: triton-util
Version: 0.0.2
Summary: Make Triton easier - A utility package for OpenAI Triton
Home-page: https://github.com/umerHA/triton_util
Author: Umer Adil
Author-email: umer.hayat.adil@gmail.com
Classifier: Programming Language :: Python :: 3
Classifier: License :: OSI Approved :: MIT License
Classifier: Operating System :: OS Independent
Requires-Python: >=3.6
Requires-Dist: triton
